hapi_schema/__init__.py
hapi_schema/_version.py
hapi_schema/db_admin1.py
hapi_schema/db_admin2.py
hapi_schema/db_conflict_event.py
hapi_schema/db_currency.py
hapi_schema/db_dataset.py
hapi_schema/db_food_price.py
hapi_schema/db_food_security.py
hapi_schema/db_funding.py
hapi_schema/db_humanitarian_needs.py
hapi_schema/db_idps.py
hapi_schema/db_location.py
hapi_schema/db_national_risk.py
hapi_schema/db_operational_presence.py
hapi_schema/db_org.py
hapi_schema/db_org_type.py
hapi_schema/db_patch.py
hapi_schema/db_population.py
hapi_schema/db_poverty_rate.py
hapi_schema/db_rainfall.py
hapi_schema/db_refugees.py
hapi_schema/db_resource.py
hapi_schema/db_returnees.py
hapi_schema/db_sector.py
hapi_schema/db_views_as_tables.py
hapi_schema/db_wfp_commodity.py
hapi_schema/db_wfp_market.py
hapi_schema/views.py
hapi_schema/utils/__init__.py
hapi_schema/utils/base.py
hapi_schema/utils/constraints.py
hapi_schema/utils/endpoint_constants.py
hapi_schema/utils/enums.py
hapi_schema/utils/hapi_views_code_generator.py
hapi_schema/utils/view_as_table_code_generator.py
hapi_schema/utils/view_as_table_definitions.toml
hapi_schema/utils/view_params.py
hapi_schema-0.9.17.dist-info/METADATA
hapi_schema-0.9.17.dist-info/WHEEL
hapi_schema-0.9.17.dist-info/licenses/LICENSE
hapi_schema-0.9.17.dist-info/RECORD
