Metadata-Version: 2.4
Name: hapi-schema
Version: 0.9.17
Summary: HAPI database schema specified in SQLAlchemy
Project-URL: Homepage, https://github.com/OCHA-DAP/hapi-schemas
Author-email: Simon Johnson <simon.johnson@un.org>
License: MIT
License-File: LICENSE
Keywords: HDX,hapi,schema
Classifier: Intended Audience :: Developers
Classifier: License :: OSI Approved :: MIT License
Classifier: Natural Language :: English
Classifier: Operating System :: MacOS
Classifier: Operating System :: Microsoft :: Windows
Classifier: Operating System :: POSIX :: Linux
Classifier: Operating System :: Unix
Classifier: Programming Language :: Python
Classifier: Programming Language :: Python :: 3
Classifier: Programming Language :: Python :: 3 :: Only
Classifier: Programming Language :: Python :: 3.8
Classifier: Programming Language :: Python :: 3.9
Classifier: Programming Language :: Python :: 3.10
Classifier: Programming Language :: Python :: 3.11
Classifier: Programming Language :: Python :: 3.12
Classifier: Topic :: Software Development :: Libraries :: Python Modules
Requires-Python: >=3.8
Requires-Dist: sqlalchemy
Provides-Extra: database
Requires-Dist: hdx-python-database>=1.3.7; extra == 'database'
Provides-Extra: dev
Requires-Dist: pre-commit; extra == 'dev'
Provides-Extra: test
Requires-Dist: hdx-python-database>=1.3.7; extra == 'test'
Requires-Dist: psycopg[binary]; extra == 'test'
Requires-Dist: pytest; extra == 'test'
Requires-Dist: pytest-cov; extra == 'test'
